drone_mobile/__init__.py
drone_mobile/async_client.py
drone_mobile/auth.py
drone_mobile/cli.py
drone_mobile/client.py
drone_mobile/const.py
drone_mobile/exceptions.py
drone_mobile/models.py
drone_mobile/vehicle.py
drone_mobile-0.3.2.dist-info/licenses/LICENSE.md
drone_mobile-0.3.2.dist-info/METADATA
drone_mobile-0.3.2.dist-info/WHEEL
drone_mobile-0.3.2.dist-info/entry_points.txt
drone_mobile-0.3.2.dist-info/top_level.txt
drone_mobile-0.3.2.dist-info/RECORD
