Metadata-Version: 2.4
Name: drone_mobile
Version: 0.3.2
Summary: Python wrapper for the DroneMobile API for Firstech/Compustar remote start systems.
Author-email: bjhiltbrand <info@bjhiltbrand.me>
License: MIT
Project-URL: Homepage, https://github.com/bjhiltbrand/drone_mobile_python
Project-URL: Documentation, https://github.com/bjhiltbrand/drone_mobile_python#readme
Project-URL: Repository, https://github.com/bjhiltbrand/drone_mobile_python
Project-URL: Bug Tracker, https://github.com/bjhiltbrand/drone_mobile_python/issues
Keywords: dronemobile,compustar,firstech,remote-start,car,vehicle
Classifier: Development Status :: 4 - Beta
Classifier: Intended Audience :: Developers
Classifier: License :: OSI Approved :: MIT License
Classifier: Operating System :: OS Independent
Classifier: Programming Language :: Python :: 3
Classifier: Programming Language :: Python :: 3.10
Classifier: Programming Language :: Python :: 3.11
Classifier: Programming Language :: Python :: 3.12
Classifier: Typing :: Typed
Requires-Python: >=3.10
License-File: LICENSE.md
Requires-Dist: requests>=2.28.0
Requires-Dist: filelock>=3.12.0
Provides-Extra: dev
Requires-Dist: pytest>=7.4.0; extra == "dev"
Requires-Dist: pytest-cov>=4.1.0; extra == "dev"
Requires-Dist: pytest-asyncio>=0.21.0; extra == "dev"
Requires-Dist: black>=23.7.0; extra == "dev"
Requires-Dist: mypy>=1.5.0; extra == "dev"
Requires-Dist: ruff>=0.0.285; extra == "dev"
Requires-Dist: pre-commit>=3.3.3; extra == "dev"
Requires-Dist: types-requests>=2.31.0; extra == "dev"
Requires-Dist: build>=1.0.0; extra == "dev"
Provides-Extra: async
Requires-Dist: aiohttp>=3.8.5; extra == "async"
Requires-Dist: aiofiles>=23.2.0; extra == "async"
Dynamic: license-file
